LICENSE
MANIFEST.in
README.rst
requirements.txt
setup.py
pybpdbjobs/__init__.py
pybpdbjobs/job.py
pybpdbjobs/jobtry.py
pybpdbjobs/parser.py
pybpdbjobs/translations.py
pybpdbjobs.egg-info/PKG-INFO
pybpdbjobs.egg-info/SOURCES.txt
pybpdbjobs.egg-info/dependency_links.txt
pybpdbjobs.egg-info/top_level.txt