Metadata-Version: 1.1
Name: pybpdbjobs
Version: 0.0.1
Summary: Library for parsing output from bpdbjbos
Home-page: http://github.com/ondmagi/pybpdbjobs
Author: Andreas Lindh
Author-email: andreas@superblock.se
License: MIT
Keywords: netbackup,bpdbjobs
Platform: UNKNOWN
Classifier: Programming Language :: Python
Classifier: Programming Language :: Python :: 2.7
Classifier: Natural Language :: English
Classifier: Intended Audience :: Developers
Classifier: License :: OSI Approved :: MIT License
Classifier: Topic :: Utilities
